machine_dialect_vm-0.1.0a2.dist-info/METADATA
machine_dialect_vm-0.1.0a2.dist-info/WHEEL
machine_dialect_vm/__init__.py
machine_dialect_vm/machine_dialect_vm.abi3.so
machine_dialect_vm-0.1.0a2.dist-info/RECORD
