Metadata-Version: 2.4
Name: machine-dialect-vm
Version: 0.1.0a2
Classifier: Development Status :: 3 - Alpha
Classifier: Intended Audience :: Developers
Classifier: License :: OSI Approved :: Apache Software License
Classifier: Programming Language :: Python :: 3
Classifier: Programming Language :: Python :: 3.10
Classifier: Programming Language :: Python :: 3.11
Classifier: Programming Language :: Python :: 3.12
Classifier: Programming Language :: Python :: 3.13
Classifier: Programming Language :: Rust
Classifier: Topic :: Software Development
Summary: High-performance Rust VM for Machine Dialect™
Keywords: programming-language,natural-language,markdown,virtual machine,vm
Author: Kenny Lajara
Requires-Python: >=3.10, <=13
